LICENSE
mehlbot/__init__.py
mehlbot/command.py
mehlbot/command_callback.py
mehlbot/logger.py
mehlbot-1.1.3.dist-info/LICENSE
mehlbot-1.1.3.dist-info/METADATA
mehlbot-1.1.3.dist-info/WHEEL
mehlbot-1.1.3.dist-info/RECORD
