Metadata-Version: 2.1
Name: mehlbot
Version: 1.1.3
Summary: A basic interface for Discord bots to handle receiving commands using the discord.py package.
Home-page: https://github.com/cobrapitz/MehlBot
License: MIT
Keywords: Discord,discord.py,Discord-Bot,Discord-Command-Bot,Python
Author: K Brandl
Author-email: kbrandla@duck.com
Requires-Python: >=3.8.1,<4.0.0
Classifier: License :: OSI Approved :: MIT License
Classifier: Programming Language :: Python :: 3
Classifier: Programming Language :: Python :: 3.9
Classifier: Programming Language :: Python :: 3.10
Classifier: Programming Language :: Python :: 3.11
Requires-Dist: discord.py (>=2.2.2,<3.0.0)
Project-URL: Documentation, https://mehlbot.readthedocs.io/en/latest/
Project-URL: Issues, https://github.com/cobrapitz/MehlBot/issues
Project-URL: Repository, https://github.com/cobrapitz/MehlBot
